odoo10_addon_web_access_rule_buttons-10.0.1.0.0-py2.7-nspkg.pth
odoo/addons/web_access_rule_buttons/README.rst
odoo/addons/web_access_rule_buttons/__init__.py
odoo/addons/web_access_rule_buttons/__manifest__.py
odoo/addons/web_access_rule_buttons/models.py
odoo/addons/web_access_rule_buttons/static/src/js/web_access_rule_buttons.js
odoo/addons/web_access_rule_buttons/views/web_access_rule_buttons.xml
odoo10_addon_web_access_rule_buttons-10.0.1.0.0.dist-info/DESCRIPTION.rst
odoo10_addon_web_access_rule_buttons-10.0.1.0.0.dist-info/METADATA
odoo10_addon_web_access_rule_buttons-10.0.1.0.0.dist-info/RECORD
odoo10_addon_web_access_rule_buttons-10.0.1.0.0.dist-info/WHEEL
odoo10_addon_web_access_rule_buttons-10.0.1.0.0.dist-info/metadata.json
odoo10_addon_web_access_rule_buttons-10.0.1.0.0.dist-info/namespace_packages.txt
odoo10_addon_web_access_rule_buttons-10.0.1.0.0.dist-info/top_level.txt
